wrblito_wait_try_utils/__init__.py
wrblito_wait_try_utils/main_module.py
wrblito_selenium_wait-0.4.dist-info/METADATA
wrblito_selenium_wait-0.4.dist-info/WHEEL
wrblito_selenium_wait-0.4.dist-info/top_level.txt
wrblito_selenium_wait-0.4.dist-info/RECORD
