Metadata-Version: 2.1
Name: wrblito-selenium-wait
Version: 0.4
Requires-Dist: selenium
